imitatus/__init__.py
imitatus/server.py
imitatus-0.1.1.dist-info/LICENSE
imitatus-0.1.1.dist-info/METADATA
imitatus-0.1.1.dist-info/WHEEL
imitatus-0.1.1.dist-info/top_level.txt
imitatus-0.1.1.dist-info/RECORD
