Metadata-Version: 2.1
Name: imitatus
Version: 0.1.1
Summary: A zero-dependency, sophisticated mock HTTP server for development and testing
Home-page: https://github.com/serkanaltuntas/imitatus
Author: Serkan Altuntas
Author-email: Serkan Altuntas <serkan@serkan.ai>
Requires-Python: >=3.8
License-File: LICENSE
